{
    "name": "root",
    "gauges": {
        "MyBehavior.Policy.Entropy.mean": {
            "value": 0.3513125777244568,
            "min": 0.21639706194400787,
            "max": 0.4380691647529602,
            "count": 35
        },
        "MyBehavior.Policy.Entropy.sum": {
            "value": 356.582275390625,
            "min": 112.14570617675781,
            "max": 390.93829345703125,
            "count": 35
        },
        "MyBehavior.Step.mean": {
            "value": 499925.0,
            "min": 465981.0,
            "max": 499925.0,
            "count": 35
        },
        "MyBehavior.Step.sum": {
            "value": 499925.0,
            "min": 465981.0,
            "max": 499925.0,
            "count": 35
        },
        "MyBehavior.Policy.ExtrinsicValueEstimate.mean": {
            "value": 38.26228332519531,
            "min": 15.847900390625,
            "max": 62.26069641113281,
            "count": 35
        },
        "MyBehavior.Policy.ExtrinsicValueEstimate.sum": {
            "value": 306.0982666015625,
            "min": 56.177146911621094,
            "max": 498.0855712890625,
            "count": 35
        },
        "MyBehavior.Policy.CuriosityValueEstimate.mean": {
            "value": 0.10677875578403473,
            "min": 0.08296775817871094,
            "max": 0.10869066417217255,
            "count": 35
        },
        "MyBehavior.Policy.CuriosityValueEstimate.sum": {
            "value": 0.8542300462722778,
            "min": 0.08971981704235077,
            "max": 0.9550306797027588,
            "count": 35
        },
        "MyBehavior.IsTraining.mean": {
            "value": 1.0,
            "min": 1.0,
            "max": 1.0,
            "count": 35
        },
        "MyBehavior.IsTraining.sum": {
            "value": 1.0,
            "min": 1.0,
            "max": 1.0,
            "count": 35
        },
        "MyBehavior.Environment.EpisodeLength.mean": {
            "value": 1910.0,
            "min": 795.0,
            "max": 2241.0,
            "count": 24
        },
        "MyBehavior.Environment.EpisodeLength.sum": {
            "value": 1910.0,
            "min": 795.0,
            "max": 2241.0,
            "count": 24
        },
        "MyBehavior.Environment.CumulativeReward.mean": {
            "value": 413.9149765968323,
            "min": 171.9309959411621,
            "max": 520.3069968223572,
            "count": 24
        },
        "MyBehavior.Environment.CumulativeReward.sum": {
            "value": 413.9149765968323,
            "min": 171.9309959411621,
            "max": 520.3069968223572,
            "count": 24
        },
        "MyBehavior.Policy.ExtrinsicReward.mean": {
            "value": 413.9149765968323,
            "min": 171.9309959411621,
            "max": 520.3069968223572,
            "count": 24
        },
        "MyBehavior.Policy.ExtrinsicReward.sum": {
            "value": 413.9149765968323,
            "min": 171.9309959411621,
            "max": 520.3069968223572,
            "count": 24
        },
        "MyBehavior.Policy.CuriosityReward.mean": {
            "value": 2.1899188309907913,
            "min": 0.0,
            "max": 3.1547031700611115,
            "count": 24
        },
        "MyBehavior.Policy.CuriosityReward.sum": {
            "value": 2.1899188309907913,
            "min": 0.0,
            "max": 3.1547031700611115,
            "count": 24
        },
        "MyBehavior.Losses.PolicyLoss.mean": {
            "value": 0.4981986875090605,
            "min": 0.3613350330689532,
            "max": 0.5024705654842231,
            "count": 8
        },
        "MyBehavior.Losses.PolicyLoss.sum": {
            "value": 0.4981986875090605,
            "min": 0.3613350330689532,
            "max": 0.5024705654842231,
            "count": 8
        },
        "MyBehavior.Losses.ValueLoss.mean": {
            "value": 357.5126228684416,
            "min": 172.9992926165913,
            "max": 483.5058871816064,
            "count": 8
        },
        "MyBehavior.Losses.ValueLoss.sum": {
            "value": 357.5126228684416,
            "min": 172.9992926165913,
            "max": 483.5058871816064,
            "count": 8
        },
        "MyBehavior.Policy.LearningRate.mean": {
            "value": 2.436997563999994e-07,
            "min": 2.436997563999994e-07,
            "max": 6.007493992599997e-06,
            "count": 8
        },
        "MyBehavior.Policy.LearningRate.sum": {
            "value": 2.436997563999994e-07,
            "min": 2.436997563999994e-07,
            "max": 6.007493992599997e-06,
            "count": 8
        },
        "MyBehavior.Policy.Epsilon.mean": {
            "value": 0.10031668,
            "min": 0.10031668,
            "max": 0.10780962000000004,
            "count": 8
        },
        "MyBehavior.Policy.Epsilon.sum": {
            "value": 0.10031668,
            "min": 0.10031668,
            "max": 0.10780962000000004,
            "count": 8
        },
        "MyBehavior.Policy.Beta.mean": {
            "value": 2.2155639999999977e-05,
            "min": 2.2155639999999977e-05,
            "max": 0.0003097692599999998,
            "count": 8
        },
        "MyBehavior.Policy.Beta.sum": {
            "value": 2.2155639999999977e-05,
            "min": 2.2155639999999977e-05,
            "max": 0.0003097692599999998,
            "count": 8
        },
        "MyBehavior.Losses.CuriosityForwardLoss.mean": {
            "value": 0.08612129158483675,
            "min": 0.07663220086661998,
            "max": 0.09236514044189176,
            "count": 8
        },
        "MyBehavior.Losses.CuriosityForwardLoss.sum": {
            "value": 0.08612129158483675,
            "min": 0.07663220086661998,
            "max": 0.09236514044189176,
            "count": 8
        },
        "MyBehavior.Losses.CuriosityInverseLoss.mean": {
            "value": 0.3727511856373614,
            "min": 0.30047152577093444,
            "max": 0.3993850009578601,
            "count": 8
        },
        "MyBehavior.Losses.CuriosityInverseLoss.sum": {
            "value": 0.3727511856373614,
            "min": 0.30047152577093444,
            "max": 0.3993850009578601,
            "count": 8
        },
        "MyBehavior.Losses.PretrainingLoss.mean": {
            "value": 0.0019720170221546596,
            "min": 0.0019720170221546596,
            "max": 0.014632555408745418,
            "count": 8
        },
        "MyBehavior.Losses.PretrainingLoss.sum": {
            "value": 0.0019720170221546596,
            "min": 0.0019720170221546596,
            "max": 0.014632555408745418,
            "count": 8
        }
    },
    "metadata": {
        "timer_format_version": "0.1.0",
        "start_time_seconds": "1662473941",
        "python_version": "3.7.13 (default, Mar 28 2022, 08:03:21) [MSC v.1916 64 bit (AMD64)]",
        "command_line_arguments": "C:\\Users\\fbga9\\miniconda3\\envs\\unityenv\\Scripts\\mlagents-learn configs/MLA-training-IT.yaml --seed 2 --run-id i-WithIncGhost-E+2.1_1 --resume",
        "mlagents_version": "0.28.0",
        "mlagents_envs_version": "0.28.0",
        "communication_protocol_version": "1.5.0",
        "pytorch_version": "1.7.1+cu110",
        "numpy_version": "1.21.6",
        "end_time_seconds": "1662475663"
    },
    "total": 1721.6152307,
    "count": 1,
    "self": 0.00645589999976437,
    "children": {
        "run_training.setup": {
            "total": 0.058934700000000007,
            "count": 1,
            "self": 0.058934700000000007
        },
        "TrainerController.start_learning": {
            "total": 1721.5498401000002,
            "count": 1,
            "self": 0.41950760000690934,
            "children": {
                "TrainerController._reset_env": {
                    "total": 17.4797452,
                    "count": 1,
                    "self": 14.4050659,
                    "children": {
                        "demo_to_buffer": {
                            "total": 3.0746792999999997,
                            "count": 1,
                            "self": 4.460000000072739e-05,
                            "children": {
                                "load_demonstration": {
                                    "total": 0.027698700000000187,
                                    "count": 1,
                                    "self": 0.0261925999999999,
                                    "children": {
                                        "read_file": {
                                            "total": 0.0015061000000002878,
                                            "count": 1,
                                            "self": 0.0015061000000002878
                                        }
                                    }
                                },
                                "make_demo_buffer": {
                                    "total": 3.0469359999999988,
                                    "count": 1,
                                    "self": 0.19517829999969116,
                                    "children": {
                                        "steps_from_proto": {
                                            "total": 2.8517577000003076,
                                            "count": 8190,
                                            "self": 0.7685321000006127,
                                            "children": {
                                                "_process_maybe_compressed_observation": {
                                                    "total": 1.4994624999997601,
                                                    "count": 16380,
                                                    "self": 0.13165509999990377,
                                                    "children": {
                                                        "_observation_to_np_array": {
                                                            "total": 1.3678073999998563,
                                                            "count": 8190,
                                                            "self": 0.0799069000000241,
                                                            "children": {
                                                                "process_pixels": {
                                                                    "total": 1.2879004999998322,
                                                                    "count": 8190,
                                                                    "self": 0.423005999999603,
                                                                    "children": {
                                                                        "image_decompress": {
                                                                            "total": 0.8648945000002293,
                                                                            "count": 8190,
                                                                            "self": 0.8648945000002293
                                                                        }
                                                                    }
                                                                }
                                                            }
                                                        }
                                                    }
                                                },
                                                "_process_rank_one_or_two_observation": {
                                                    "total": 0.5837630999999348,
                                                    "count": 49140,
                                                    "self": 0.5837630999999348
                                                }
                                            }
                                        }
                                    }
                                }
                            }
                        }
                    }
                },
                "TrainerController.advance": {
                    "total": 1690.7093937999932,
                    "count": 34221,
                    "self": 0.4274134999918715,
                    "children": {
                        "env_step": {
                            "total": 488.52094109999825,
                            "count": 34221,
                            "self": 164.98448950001153,
                            "children": {
                                "SubprocessEnvManager._take_step": {
                                    "total": 323.1626120999989,
                                    "count": 34221,
                                    "self": 1.258552400002543,
                                    "children": {
                                        "TorchPolicy.evaluate": {
                                            "total": 321.90405969999637,
                                            "count": 34200,
                                            "self": 25.389903700002662,
                                            "children": {
                                                "TorchPolicy.sample_actions": {
                                                    "total": 296.5141559999937,
                                                    "count": 34200,
                                                    "self": 296.5141559999937
                                                }
                                            }
                                        }
                                    }
                                },
                                "workers": {
                                    "total": 0.37383949998779187,
                                    "count": 34221,
                                    "self": 0.0,
                                    "children": {
                                        "worker_root": {
                                            "total": 1684.0792807999965,
                                            "count": 34221,
                                            "is_parallel": true,
                                            "self": 1540.5786681999875,
                                            "children": {
                                                "steps_from_proto": {
                                                    "total": 0.009181500000000398,
                                                    "count": 1,
                                                    "is_parallel": true,
                                                    "self": 0.00016550000000137288,
                                                    "children": {
                                                        "_process_maybe_compressed_observation": {
                                                            "total": 0.008872599999998343,
                                                            "count": 2,
                                                            "is_parallel": true,
                                                            "self": 3.5399999999796705e-05,
                                                            "children": {
                                                                "_observation_to_np_array": {
                                                                    "total": 0.008837199999998546,
                                                                    "count": 1,
                                                                    "is_parallel": true,
                                                                    "self": 1.8899999998822636e-05,
                                                                    "children": {
                                                                        "process_pixels": {
                                                                            "total": 0.008818299999999724,
                                                                            "count": 1,
                                                                            "is_parallel": true,
                                                                            "self": 0.00015319999999974243,
                                                                            "children": {
                                                                                "image_decompress": {
                                                                                    "total": 0.008665099999999981,
                                                                                    "count": 1,
                                                                                    "is_parallel": true,
                                                                                    "self": 0.008665099999999981
                                                                                }
                                                                            }
                                                                        }
                                                                    }
                                                                }
                                                            }
                                                        },
                                                        "_process_rank_one_or_two_observation": {
                                                            "total": 0.00014340000000068187,
                                                            "count": 6,
                                                            "is_parallel": true,
                                                            "self": 0.00014340000000068187
                                                        }
                                                    }
                                                },
                                                "UnityEnvironment.step": {
                                                    "total": 143.49143110000892,
                                                    "count": 34221,
                                                    "is_parallel": true,
                                                    "self": 1.8361161000095763,
                                                    "children": {
                                                        "UnityEnvironment._generate_step_input": {
                                                            "total": 1.3933529999998235,
                                                            "count": 34221,
                                                            "is_parallel": true,
                                                            "self": 1.3933529999998235
                                                        },
                                                        "communicator.exchange": {
                                                            "total": 124.9978331999952,
                                                            "count": 34221,
                                                            "is_parallel": true,
                                                            "self": 124.9978331999952
                                                        },
                                                        "steps_from_proto": {
                                                            "total": 15.264128800004322,
                                                            "count": 34221,
                                                            "is_parallel": true,
                                                            "self": 4.234422899975993,
                                                            "children": {
                                                                "_process_maybe_compressed_observation": {
                                                                    "total": 7.875654100007715,
                                                                    "count": 68442,
                                                                    "is_parallel": true,
                                                                    "self": 0.7623260999950148,
                                                                    "children": {
                                                                        "_observation_to_np_array": {
                                                                            "total": 7.1133280000127,
                                                                            "count": 34224,
                                                                            "is_parallel": true,
                                                                            "self": 0.421136100022256,
                                                                            "children": {
                                                                                "process_pixels": {
                                                                                    "total": 6.692191899990444,
                                                                                    "count": 34224,
                                                                                    "is_parallel": true,
                                                                                    "self": 2.048816899997963,
                                                                                    "children": {
                                                                                        "image_decompress": {
                                                                                            "total": 4.643374999992481,
                                                                                            "count": 34224,
                                                                                            "is_parallel": true,
                                                                                            "self": 4.643374999992481
                                                                                        }
                                                                                    }
                                                                                }
                                                                            }
                                                                        }
                                                                    }
                                                                },
                                                                "_process_rank_one_or_two_observation": {
                                                                    "total": 3.154051800020614,
                                                                    "count": 205326,
                                                                    "is_parallel": true,
                                                                    "self": 3.154051800020614
                                                                }
                                                            }
                                                        }
                                                    }
                                                }
                                            }
                                        }
                                    }
                                }
                            }
                        },
                        "trainer_advance": {
                            "total": 1201.761039200003,
                            "count": 34221,
                            "self": 0.551142199967444,
                            "children": {
                                "process_trajectory": {
                                    "total": 615.8951611000354,
                                    "count": 34221,
                                    "self": 605.3080363000355,
                                    "children": {
                                        "RLTrainer._checkpoint": {
                                            "total": 10.587124799999856,
                                            "count": 1,
                                            "self": 10.587124799999856
                                        }
                                    }
                                },
                                "_update_policy": {
                                    "total": 585.3147359000002,
                                    "count": 8,
                                    "self": 73.30727449999654,
                                    "children": {
                                        "TorchPPOOptimizer.update": {
                                            "total": 493.72908680000194,
                                            "count": 4160,
                                            "self": 493.72908680000194
                                        },
                                        "TorchPolicy.sample_actions": {
                                            "total": 18.27837460000174,
                                            "count": 2048,
                                            "self": 18.27837460000174
                                        }
                                    }
                                }
                            }
                        }
                    }
                },
                "trainer_threads": {
                    "total": 6.000000212225132e-07,
                    "count": 1,
                    "self": 6.000000212225132e-07
                },
                "TrainerController._save_models": {
                    "total": 12.941192900000033,
                    "count": 1,
                    "self": 0.048710499999970125,
                    "children": {
                        "RLTrainer._checkpoint": {
                            "total": 12.892482400000063,
                            "count": 1,
                            "self": 12.892482400000063
                        }
                    }
                }
            }
        }
    }
}